ifigure/__init__.py
ifigure/__main__.py
ifigure/client.py
ifigure/events.py
ifigure/ifigure_app.py
ifigure/ifigure_app_macport_fix.py
ifigure/ifigure_config.py
ifigure/interactive.py
ifigure/numerical_function.py
ifigure/piscope.py
ifigure/server.py
ifigure/startup.py
ifigure/add_on/__init__.py
ifigure/add_on/model/__init__.py
ifigure/add_on/model/module/__init__.py
ifigure/add_on/model/module/csv.py
ifigure/add_on/model/module/efit_afile.py
ifigure/add_on/model/module/efit_gfile.py
ifigure/add_on/model/module/efit_pfile.py
ifigure/add_on/model/module/idl_save.py
ifigure/add_on/model/module/matlab_mat.py
ifigure/add_on/model/module/mdsplus_tree.py
ifigure/add_on/model/module/name_list.py
ifigure/add_on/model/module/netcdf4.py
ifigure/add_on/model/module/tsc_input.py
ifigure/add_on/model/module/subs/__init__.py
ifigure/add_on/model/module/subs/dwscope_sub.py
ifigure/add_on/model/module/subs/dwscope_subs.py
ifigure/add_on/model/module/subs/idl_save_subs.py
ifigure/add_on/model/module/subs/mdsplus_tree_node.py
ifigure/add_on/model/module/subs/netcdf_node.py
ifigure/add_on/model/script/__init__.py
ifigure/add_on/setting/__init__.py
ifigure/add_on/setting/module/__init__.py
ifigure/add_on/setting/module/cmod_pyro.py
ifigure/add_on/setting/module/connection.py
ifigure/add_on/setting/module/mdsplus_worker.py
ifigure/add_on/setting/module/ssh.py
ifigure/add_on/setting/script/__init__.py
ifigure/add_on/solver/__init__.py
ifigure/add_on/solver/module/__init__.py
ifigure/add_on/solver/script/__init__.py
ifigure/add_on/solver/script/cost_optimizer.py
ifigure/add_on/solver/script/def_script.py
ifigure/add_on/solver/script/genray_loki.py
ifigure/add_on/solver/script/merge_sol.py
ifigure/add_on/solver/script/merge_sol_parametric.py
ifigure/add_on/solver/script/merge_sol_std.py
ifigure/add_on/solver/script/run_optimizer.py
ifigure/add_on/solver/script/run_parametric.py
ifigure/add_on/solver/script/run_stdsolver.py
ifigure/add_on/solver/script/genray_cql3d_loki/rec_nc_files.py
piscope-1.2.2.dist-info/licenses/LICENSE
piscope-1.2.2.dist-info/METADATA
piscope-1.2.2.dist-info/WHEEL
piscope-1.2.2.dist-info/entry_points.txt
piscope-1.2.2.dist-info/top_level.txt
piscope-1.2.2.dist-info/RECORD
