Metadata-Version: 2.4
Name: piScope
Version: 1.2.2
Summary: piScope data analysis workbench
Author: S. Shiraiwa
Maintainer-email: "S. Shiraiwa" <shiraiwa@princeton.edu>
License-Expression: GPL-3.0-only
Project-URL: Homepage, https://github.com/piScope
Project-URL: Download, https://github.com/piScope
Keywords: scientific computing,python visualzation,finite element method
Classifier: Development Status :: 5 - Production/Stable
Classifier: Intended Audience :: Developers
Classifier: Topic :: Scientific/Engineering :: Physics
Classifier: Programming Language :: Python :: 3.11
Classifier: Programming Language :: Python :: 3.12
Requires-Python: >=3.11
License-File: LICENSE
Requires-Dist: numpy>=2.3.0
Requires-Dist: scipy
Requires-Dist: matplotlib>=3.10.3
Requires-Dist: PyOpenGL
Requires-Dist: netCDF4
Requires-Dist: h5py
Requires-Dist: PyPDF2
Requires-Dist: pdfrw
Requires-Dist: wxPython
Requires-Dist: future
Requires-Dist: autopep8
Requires-Dist: scipy
Dynamic: license-file
